{
  "rulesByType": {
    "context": [
      { "id": 1, "question": "Very old thing (older than 1000 years)?", "difficulty": 2 },
      { "id": 2, "question": "New thing (made after 1950)?", "difficulty": 2 },
      { "id": 3, "question": "Found in most homes?", "difficulty": 1 },
      { "id": 4, "question": "Rare item most people don't have?", "difficulty": 1 },
      { "id": 5, "question": "Mainly for kids?", "difficulty": 1 },
      { "id": 6, "question": "Made for grown-ups?", "difficulty": 1 },
      { "id": 7, "question": "Fancy or expensive item?", "difficulty": 2 },
      { "id": 8, "question": "Something everyone needs?", "difficulty": 2 },
      { "id": 9, "question": "Useful for getting things done?", "difficulty": 2 },
      { "id": 10, "question": "Looking nice?", "difficulty": 1 },
      { "id": 11, "question": "Found in nature?", "difficulty": 1 },
      { "id": 12, "question": "Made in a factory?", "difficulty": 2 },
      { "id": 13, "question": "Used for special events?", "difficulty": 2 },
      { "id": 14, "question": "Used every day?", "difficulty": 1 },
      { "id": 15, "question": "Belongs to one person?", "difficulty": 2 },
      { "id": 16, "question": "Shared by many people?", "difficulty": 2 },
      { "id": 17, "question": "High-tech?", "difficulty": 2 },
      { "id": 18, "question": "Simple machine or tool?", "difficulty": 2 },
      { "id": 19, "question": "From a specific country or culture?", "difficulty": 3 },
      { "id": 20, "question": "Found in many countries?", "difficulty": 2 },
      { "id": 21, "question": "Throw away after using?", "difficulty": 1 },
      { "id": 22, "question": "Lasts for many years?", "difficulty": 2 },
      { "id": 23, "question": "Used inside buildings?", "difficulty": 1 },
      { "id": 24, "question": "Used outside?", "difficulty": 1 },
      { "id": 25, "question": "Used in movies or TV shows?", "difficulty": 2 },
      { "id": 26, "question": "Used by people with different jobs?", "difficulty": 3 },
      { "id": 27, "question": "Has religious meaning?", "difficulty": 3 },
      { "id": 28, "question": "Not connected to religion?", "difficulty": 3 },
      { "id": 29, "question": "Made by machines in large numbers?", "difficulty": 2 },
      { "id": 30, "question": "Made by hand?", "difficulty": 2 },
      { "id": 31, "question": "Makes people happy?", "difficulty": 2 },
      { "id": 32, "question": "Can be scary or dangerous?", "difficulty": 2 },
      { "id": 33, "question": "For fun or games?", "difficulty": 1 },
      { "id": 34, "question": "For work or important tasks?", "difficulty": 2 },
      { "id": 35, "question": "Only used during certain times of year?", "difficulty": 2 },
      { "id": 36, "question": "Used all year round?", "difficulty": 1 },
      { "id": 37, "question": "Need to learn how to use it?", "difficulty": 2 },
      { "id": 38, "question": "Easy for anyone to use?", "difficulty": 1 },
      { "id": 39, "question": "Used in official or formal places?", "difficulty": 3 },
      { "id": 40, "question": "Used in relaxed, casual settings?", "difficulty": 2 },
      { "id": 41, "question": "People like to collect these?", "difficulty": 2 },
      { "id": 42, "question": "Part of special traditions?", "difficulty": 3 },
      { "id": 43, "question": "Important in history?", "difficulty": 3 },
      { "id": 44, "question": "Mainly used now, not in the past?", "difficulty": 3 },
      { "id": 45, "question": "Often given as a present?", "difficulty": 2 },
      { "id": 46, "question": "Rarely given as a present?", "difficulty": 2 },
      { "id": 47, "question": "Owned by rich people?", "difficulty": 2 },
      { "id": 48, "question": "Used by people of all income levels?", "difficulty": 3 },
      { "id": 49, "question": "Shows up in books, movies, or art?", "difficulty": 2 },
      { "id": 50, "question": "Not famous in stories or pictures?", "difficulty": 2 }
    ],
    "property": [
      { "id": 51, "question": "Breaks easily?", "difficulty": 2 },
      { "id": 52, "question": "Easy to carry around?", "difficulty": 1 },
      { "id": 53, "question": "Needs electricity to work?", "difficulty": 1 },
      { "id": 54, "question": "Costs a lot of money?", "difficulty": 2 },
      { "id": 55, "question": "Found in nature?", "difficulty": 1 },
      { "id": 56, "question": "Stays dry in water?", "difficulty": 2 },
      { "id": 57, "question": "Floats in water?", "difficulty": 2 },
      { "id": 58, "question": "Made of metal?", "difficulty": 1 },
      { "id": 59, "question": "Makes noise when used?", "difficulty": 1 },
      { "id": 60, "question": "Has bright colors?", "difficulty": 1 },
      { "id": 61, "question": "Can be recycled?", "difficulty": 2 },
      { "id": 62, "question": "See-through?", "difficulty": 1 },
      { "id": 63, "question": "Has moving parts?", "difficulty": 1 },
      { "id": 64, "question": "Soft to touch?", "difficulty": 1 },
      { "id": 65, "question": "Can be folded or squished?", "difficulty": 1 },
      { "id": 66, "question": "Needs to be taken care of?", "difficulty": 2 },
      { "id": 67, "question": "Has sharp edges?", "difficulty": 2 },
      { "id": 68, "question": "Can be eaten?", "difficulty": 1 },
      { "id": 69, "question": "Has a strong smell?", "difficulty": 1 },
      { "id": 70, "question": "Heavy to lift?", "difficulty": 1 },
      { "id": 71, "question": "Can be worn?", "difficulty": 1 },
      { "id": 72, "question": "Makes heat?", "difficulty": 2 },
      { "id": 73, "question": "Can catch fire?", "difficulty": 2 },
      { "id": 74, "question": "Can be changed or decorated?", "difficulty": 2 },
      { "id": 75, "question": "Needs to be put together?", "difficulty": 2 },
      { "id": 76, "question": "Breaks down in nature?", "difficulty": 3 },
      { "id": 77, "question": "Can be stacked?", "difficulty": 2 },
      { "id": 78, "question": "Shiny or reflects light?", "difficulty": 2 },
      { "id": 79, "question": "Sticks to magnets?", "difficulty": 2 },
      { "id": 80, "question": "Can be painted?", "difficulty": 2 },
      { "id": 81, "question": "Soaks up water?", "difficulty": 2 },
      { "id": 82, "question": "Bends easily?", "difficulty": 1 },
      { "id": 83, "question": "Changes color when wet?", "difficulty": 2 },
      { "id": 84, "question": "Changes over time?", "difficulty": 3 },
      { "id": 85, "question": "Same shape on both sides?", "difficulty": 2 },
      { "id": 86, "question": "Can be fixed if broken?", "difficulty": 2 },
      { "id": 87, "question": "Needs fuel to work?", "difficulty": 2 },
      { "id": 88, "question": "Clean and germ-free?", "difficulty": 2 },
      { "id": 89, "question": "Works underwater?", "difficulty": 2 },
      { "id": 90, "question": "Has wheels?", "difficulty": 1 },
      { "id": 91, "question": "Made to throw away?", "difficulty": 1 },
      { "id": 92, "question": "Can be heated safely?", "difficulty": 3 },
      { "id": 93, "question": "Needs special storage?", "difficulty": 2 },
      { "id": 94, "question": "Made by hand?", "difficulty": 2 },
      { "id": 95, "question": "Easy to clean?", "difficulty": 1 },
      { "id": 96, "question": "Comes in pairs?", "difficulty": 1 },
      { "id": 97, "question": "Used in certain seasons?", "difficulty": 2 },
      { "id": 98, "question": "Can be used as a tool?", "difficulty": 2 },
      { "id": 99, "question": "Needs permission to use?", "difficulty": 3 },
      { "id": 100, "question": "Can be used many times?", "difficulty": 1 }
    ],
    "wording": [
      { "id": 101, "question": "Has exactly two syllables?", "difficulty": 3 },
      { "id": 102, "question": "Starts with a vowel (a,e,i,o,u)?", "difficulty": 2 },
      { "id": 103, "question": "Ends with a consonant?", "difficulty": 2 },
      { "id": 104, "question": "Has exactly five letters?", "difficulty": 2 },
      { "id": 105, "question": "Contains both 'a' and 'e'?", "difficulty": 3 },
      { "id": 106, "question": "First letter comes before last letter in alphabet?", "difficulty": 4 },
      { "id": 107, "question": "Made of two words put together?", "difficulty": 2 },
      { "id": 108, "question": "Has a double letter?", "difficulty": 3 },
      { "id": 109, "question": "Starts with a letter from A to M?", "difficulty": 3 },
      { "id": 110, "question": "Has more than six letters?", "difficulty": 2 },
      { "id": 111, "question": "Can be both a noun and verb?", "difficulty": 4 },
      { "id": 112, "question": "Contains letter 'k'?", "difficulty": 2 },
      { "id": 113, "question": "Has 4 or fewer unique letters?", "difficulty": 4 },
      { "id": 114, "question": "Has a prefix?", "difficulty": 4 },
      { "id": 115, "question": "Has both letters 'a' and 'b'?", "difficulty": 3 },
      { "id": 116, "question": "First two letters are in alphabetic order?", "difficulty": 4 },
      { "id": 117, "question": "Has the letter 'r'?", "difficulty": 2 },
      { "id": 118, "question": "Has three or more consonants in a row?", "difficulty": 4 },
      { "id": 119, "question": "Has exactly 6-8 letters?", "difficulty": 3 },
      { "id": 120, "question": "Has a suffix?", "difficulty": 4 },
      { "id": 121, "question": "Has two letters 't', 'v' and 's'?", "difficulty": 5 },
      { "id": 122, "question": "Contains letter 'z'?", "difficulty": 2 },
      { "id": 123, "question": "Has a repeated letter?", "difficulty": 3 },
      { "id": 124, "question": "Has exactly three syllables?", "difficulty": 3 },
      { "id": 125, "question": "Contains a color name ('red' in 'credit')?", "difficulty": 5 },
      { "id": 126, "question": "Has a silent consonant?", "difficulty": 4 },
      { "id": 127, "question": "Describes actions (verb)?", "difficulty": 3 },
      { "id": 128, "question": "Ends with 'er'?", "difficulty": 2 },
      { "id": 129, "question": "Has all letters in alphabetical order?", "difficulty": 5 },
      { "id": 130, "question": "Has two vowel sounds together?", "difficulty": 4 },
      { "id": 131, "question": "All letters appear exactly once?", "difficulty": 4 },
      { "id": 132, "question": "Contains letter 'q'?", "difficulty": 2 },
      { "id": 133, "question": "Contains at least 3 vowels?", "difficulty": 3 },
      { "id": 134, "question": "Has more vowels than consonants?", "difficulty": 3 },
      { "id": 135, "question": "Has an even number of letters?", "difficulty": 2 },
      { "id": 136, "question": "Has exactly two vowels?", "difficulty": 3 },
      { "id": 137, "question": "Last letter comes before middle letter in alphabet?", "difficulty": 5 },
      { "id": 138, "question": "Ends with a vowel?", "difficulty": 2 },
      { "id": 139, "question": "Starts and ends with the same letter?", "difficulty": 3 },
      { "id": 140, "question": "Has just one syllable?", "difficulty": 2 },
      { "id": 141, "question": "Made from first letters of words?", "difficulty": 4 },
      { "id": 142, "question": "Contains 'th'?", "difficulty": 2 },
      { "id": 143, "question": "Has at least one letter that appears twice?", "difficulty": 3 },
      { "id": 144, "question": "Has letter 'y'?", "difficulty": 2 },
      { "id": 145, "question": "First and last letters are consonants?", "difficulty": 3 },
      { "id": 146, "question": "Contains 'sh' or 'ch'?", "difficulty": 2 },
      { "id": 147, "question": "Has all letters from first half of alphabet?", "difficulty": 5 },
      { "id": 148, "question": "Ends with 'ly'?", "difficulty": 2 },
      { "id": 149, "question": "Contains a number or digit when spelled?", "difficulty": 5 },
      { "id": 150, "question": "Has more consonants than vowels?", "difficulty": 3 }
    ]
  }
} 